Workbook

Sheet Dashboard Summary
A1: 2026 - Farm Management & Enterprise Master Dashboard - 2026
A4: Crop Type | B4: Total Area (ha) | C4: Avg Yield (t/ha) | D4: Total Inputs ($) | E4: Gross Revenue ($) | F4: Net Profit ($) | G4: Net Profit ($/ha)
A5: Wheat | B5: 800 | C5: 4.2 | D5: =SUMIF('Paddock & Crop Log'!D:D, A5, 'Paddock & Crop Log'!Q:Q) -> #N/A | E5: =SUMIF('Harvest Ledger'!B:B, A5, 'Harvest Ledger'!G:G) -> 114240 | F5: =E5-D5 -> #N/A | G5: =IF(B5>0, F5/B5, 0) -> #N/A
A6: Barley | B6: 678 | C6: 5.8 | D6: =SUMIF('Paddock & Crop Log'!D:D, A6, 'Paddock & Crop Log'!Q:Q) -> #N/A | E6: =SUMIF('Harvest Ledger'!B:B, A6, 'Harvest Ledger'!G:G) -> 182700 | F6: =E6-D6 -> #N/A | G6: =IF(B6>0, F6/B6, 0) -> #N/A
A7: Canola | B7: 805 | C7: 2.1 | D7: =SUMIF('Paddock & Crop Log'!D:D, A7, 'Paddock & Crop Log'!Q:Q) -> 0 | E7: =SUMIF('Harvest Ledger'!B:B, A7, 'Harvest Ledger'!G:G) -> 0 | F7: =E7-D7 -> 0 | G7: =IF(B7>0, F7/B7, 0) -> 0
A8: Lentils | B8: 245 | C8: 1.34 | D8: =SUMIF('Paddock & Crop Log'!D:D, A8, 'Paddock & Crop Log'!Q:Q) -> 0 | E8: =SUMIF('Harvest Ledger'!B:B, A8, 'Harvest Ledger'!G:G) -> 0 | F8: =E8-D8 -> 0 | G8: =IF(B8>0, F8/B8, 0) -> 0

Sheet Asset Management
A1: Machinery Asset Management & True Hourly Operating Costs
A3: Asset ID | B3: Description | C3: Purchase Price ($) | D3: Current Age (yrs) | E3: Lifespan (yrs) | F3: Salvage Value ($) | G3: Annual Write-down ($) | H3: Avg Annual Use (hrs) | I3: Service Costs | J3: Annual Maintenance | K3: Hourly Depreciation ($/hr) | L3: Est Fuel & Maint ($/hr) | M3: Total Op Cost ($/hr)
A4: QUAD01 | B4: 450 Case QuadTrac | C4: 280000 | D4: 4 | E4: 15 | F4: 60000 | G4: =(C4-F4)/E4 -> 14666.667 | H4: 500 | I4: 1200 | K4: =G4/H4 -> 29.333333 | L4: 45 | M4: =K4+L4 -> 74.333333
A5: HARV01 | B5: Class 8 Combine Harvester | C5: 520000 | D5: 2 | E5: 10 | F5: 120000 | G5: =(C5-F5)/E5 -> 40000 | H5: 300 | I5: 1200 | J5: 20000 | K5: =G5/H5 -> 133.33333 | L5: 75 | M5: =K5+L5 -> 208.33333
A6: SPRA01 | B6: 36m Self-Propelled Sprayer | C6: 340000 | D6: 3 | E6: 12 | F6: 80000 | G6: =(C6-F6)/E6 -> 21666.667 | H6: 400 | I6: 1200 | K6: =G6/H6 -> 54.166667 | L6: 35 | M6: =K6+L6 -> 89.166667
A7: SEED01 | B7: JD Air Seeder | J7: 5000
A8: SPRE01 | B8: Spreader | J8: 300
A9: MAGN01 | B9: 280 Case Magnum | I9: 1200

Sheet Paddock & Crop Log
A1: Master Paddock Log: Inputs, Chemical & Fertilizer Rates per Hectare
A3: Log ID | B3: Paddock Name | C3: Size (ha) | D3: Crop Type | E3: Operation | F3: Machine ID | G3: Hours Spent | H3: Machine Cost ($) | I3: Fert Type | J3: Fert Rate (kg/ha) | K3: Total Fert (kg) | L3: Fert $/kg | M3: Chem Type | N3: Chem Rate (L/ha) | O3: Total Chem (L) | P3: Chem $/L | Q3: Total Inputs ($) | R3: Yield (t/ha)
A4: L001 | B4: North Boundary | C4: 120 | D4: Wheat | E4: Sowing | F4: TRAC01 | G4: 12 | H4: =G4*VLOOKUP(F4,'Asset Management'!A:M,11,FALSE) -> #N/A | I4: Urea | J4: 80 | K4: =C4*J4 -> 9600 | L4: 0.65 | M4: Trifluralin | N4: 1.5 | O4: =C4*N4 -> 180 | P4: 4.5 | Q4: =H4+(K4*L4)+(O4*P4) -> #N/A | R4: 2.8
A5: L002 | B5: Home Block | C5: 150 | D5: Barley | E5: Sowing | F5: TRAC01 | G5: 15 | H5: =G5*VLOOKUP(F5,'Asset Management'!A:M,11,FALSE) -> #N/A | I5: DAP | J5: 70 | K5: =C5*J5 -> 10500 | L5: 0.85 | M5: Prosaro | N5: 1 | O5: =C5*N5 -> 150 | P5: 12 | Q5: =H5+(K5*L5)+(O5*P5) -> #N/A | R5: 4.2

Sheet Chemical Records
A1: Chemical Log: Chemical per Hectare
D3: Audit - (standard delivery vessel)
B4: Chem Type | C4: Chem Type | D4: Start of 2026 | E4: Current | F4: Required | G4: Order? | H4: Required by | I4: Crops to use on | J4: Cost per Drum
B5: Herbicide | C5: Glyphosate | D5: 8 | E5: 10 | F5: 10 | G5: Yes | H5: Start of August | I5: Wheat, Canola, Barley | J5: 4000
B6: Fungacide | C6: Prothioconazole | D6: 4 | E6: 12 | F6: 12 | G6: No | H6: Start of August | I6: Wheat, Canola, Barley | J6: 4000
B7: Herbicide | C7: Imazamox + Imazapyr | D7: 4 | E7: 12 | F7: 12 | G7: Yes | H7: Start of August | I7: Wheat, Canola, Barley | J7: 4001

Sheet Harvest Plan & Inputs
A1: Harvest Inputs Ledger
A3: Harvest Order | B3: Harvest Commence Date | C3: Harvest Finish Date | D3: Night Paddock Move | E3: Paddock Name | F3: Crop Type | G3: Grain Variety | H3: Quality | I3: Size (ha) | J3: HA / Rotar Hour | K3: Yield / ha (t/ha) | L3: Total Yield (t) | M3: Fuel/ha (l) | N3: Total Fuel (l) | O3: Avg Fuel Price | P3: Fuel Bill | Q3: Header Contractor | R3: Email | S3: Phone | T3: Header Contractors Price / Rotar Hour | U3: Starting Rotar Hours | V3: Finishing Rotar Hours | W3: Rotar Hours | X3: Header Contractors Total Price | Y3: Contractor Paid | Z3: Staff Cost per hour | AA3: Staff Cost per day | AB3: Staff Number | AC3: Total Staff per day
A4: 1 | B4: 46337 | C4: 46337 | D4: NA | E4: North Boundary | F4: Wheat | G4: Calibre | H4: ASW1 | I4: 120 | J4: 10 | K4: 4.1 | L4: =SUM(K4*I4) -> 492 | M4: 50 | N4: =SUM(M4*I4) -> 6000 | O4: 2.2 | P4: =SUM(N4*O4) -> 13200 | Q4: AA Harvesting | R4: aa@gmail.com | S4: 0400000000 | T4: 650 | U4: 123 | V4: 130.1 | W4: =SUM(V4-U4) -> 7.1 | X4: =SUM(T4*W4) -> 4615 | Y4: No | Z4: 35 | AA4: =SUM(Z4*16) -> 560 | AB4: 3 | AC4: =SUM(AA4*AB4) -> 1680
A5: 2 | B5: 46337 | C5: 46338 | D5: No | E5: Home Block 1 | F5: Barley | G5: Maximus CL | H5: Malting | I5: 150 | J5: 10 | K5: 5.81 | L5: =SUM(K5*I5) -> 871.5 | M5: 50 | N5: =SUM(M5*I5) -> 7500 | O5: 2.2 | P5: =SUM(N5*O5) -> 16500 | Q5: AA Harvesting | R5: aa@gmail.com | S5: 0400000000 | T5: 650 | U5: 130.1 | V5: 142 | W5: =SUM(V5-U5) -> 11.9 | X5: =SUM(T5*W5) -> 7735 | Y5: No | Z5: 35 | AA5: =SUM(Z5*16) -> 560 | AB5: 3 | AC5: =SUM(AA5*AB5) -> 1680
A6: 3 | B6: 46338 | C6: 46338 | D6: Yes | E6: Home Block 2 | F6: Barley | H6: Feed

Sheet Harvest Ledger
A1: Harvest Production Ledger & Commodity Value Trading
A3: Paddock Name | B3: Crop Type | C3: Total Yield (t) | D3: Yield per Hectare (t/ha) | E3: Grain Grade | F3: Price Received ($/t) | G3: Gross Revenue ($)
A4: North Boundary | B4: Wheat | C4: 336 | D4: =C4/VLOOKUP(A4,'Paddock & Crop Log'!B:C,2,FALSE) -> 2.8 | E4: APW1 | F4: 340 | G4: =C4*F4 -> 114240
A5: Home Block | B5: Barley | C5: 630 | D5: =C5/VLOOKUP(A5,'Paddock & Crop Log'!B:C,2,FALSE) -> 4.2 | E5: BAR1 | F5: 290 | G5: =C5*F5 -> 182700

Sheet Silo Management
C2: Silo 1 | E2: Silo 2 | G2: Silo 3 | I2: Silo 4 | K2: Silo 5 | M2: Silo 6 | O2: Silo 7 | Q2: Silo 8 | S2: Silo 9 | U2: Silo 10
B3: Capacity (t) | C3: 120 | E3: 120 | G3: 120 | I3: 120 | K3: 120 | M3: 120 | O3: 120 | Q3: 120 | S3: 120 | U3: 120
B4: Product | C4: Wheat | E4: Wheat | G4: Wheat | I4: Wheat | K4: Wheat | M4: Barley | O4: Barley | Q4: Barley | S4: Barley | U4: Barley
B5: Approx tonnes | C5: 110 | E5: 100
B6: Paddock Source | C6: North Boundary | E6: North Boundary
B7: Approx Avg Moisture | C7: 0.147 | E7: 0.144
B8: Grain Price | C8: 400 | E8: 400
B9: Silo Value | C9: =SUM(C5*C8) -> 44000 | E9: =SUM(E5*E8) -> 40000
B10: Allocated Buyer | C10: Seed | E10: XX Melbourne | M10: Seed
